<?xml version="1.0" encoding="UTF-8"?>
<!DOCTYPE mapper PUBLIC "-//mybatis.org//DTD Mapper 3.0//EN" "http://mybatis.org/dtd/mybatis-3-mapper.dtd">
<mapper namespace="cbs.repository.code.dao.ActeryMapper">
  <resultMap id="BaseResultMap" type="cbs.repository.code.model.Actery">
    <!--
      WARNING - @mbggenerated
      This element is automatically generated by MyBatis Generator, do not modify.
      This element was generated on Sun Nov 21 21:36:06 CST 2010.
    -->
    <result column="PRDCDE" jdbcType="VARCHAR" property="prdcde" />
    <result column="EVTCDE" jdbcType="VARCHAR" property="evtcde" />
    <result column="CTPCDE" jdbcType="VARCHAR" property="ctpcde" />
    <result column="CATCDE" jdbcType="VARCHAR" property="catcde" />
    <result column="ERYSEQ" jdbcType="DECIMAL" property="eryseq" />
    <result column="ORGIDT" jdbcType="VARCHAR" property="orgidt" />
    <result column="CUSIDT" jdbcType="VARCHAR" property="cusidt" />
    <result column="APCODE" jdbcType="VARCHAR" property="apcode" />
    <result column="CURCDE" jdbcType="VARCHAR" property="curcde" />
    <result column="ERYAMT" jdbcType="VARCHAR" property="eryamt" />
    <result column="CDRFLG" jdbcType="DECIMAL" property="cdrflg" />
    <result column="VCHPAR" jdbcType="VARCHAR" property="vchpar" />
    <result column="TOTNUM" jdbcType="DECIMAL" property="totnum" />
    <result column="CORCUR" jdbcType="VARCHAR" property="corcur" />
    <result column="CORAPC" jdbcType="VARCHAR" property="corapc" />
    <result column="ERYREM" jdbcType="VARCHAR" property="eryrem" />
    <result column="AMDTLR" jdbcType="VARCHAR" property="amdtlr" />
    <result column="UPDDAT" jdbcType="TIMESTAMP" property="upddat" />
    <result column="RECSTS" jdbcType="VARCHAR" property="recsts" />
  </resultMap>
  <sql id="Example_Where_Clause">
    <!--
      WARNING - @mbggenerated
      This element is automatically generated by MyBatis Generator, do not modify.
      This element was generated on Sun Nov 21 21:36:06 CST 2010.
    -->
    <where>
      <foreach collection="oredCriteria" item="criteria" separator="or">
        <if test="criteria.valid">
          <trim prefix="(" prefixOverrides="and" suffix=")">
            <foreach collection="criteria.criteria" item="criterion">
              <choose>
                <when test="criterion.noValue">
                  and ${criterion.condition}
                </when>
                <when test="criterion.singleValue">
                  and ${criterion.condition} #{criterion.value}
                </when>
                <when test="criterion.betweenValue">
                  and ${criterion.condition} #{criterion.value} and #{criterion.secondValue}
                </when>
                <when test="criterion.listValue">
                  and ${criterion.condition}
                  <foreach close=")" collection="criterion.value" item="listItem" open="(" separator=",">
                    #{listItem}
                  </foreach>
                </when>
              </choose>
            </foreach>
          </trim>
        </if>
      </foreach>
    </where>
  </sql>
  <sql id="Update_By_Example_Where_Clause">
    <!--
      WARNING - @mbggenerated
      This element is automatically generated by MyBatis Generator, do not modify.
      This element was generated on Sun Nov 21 21:36:06 CST 2010.
    -->
    <where>
      <foreach collection="example.oredCriteria" item="criteria" separator="or">
        <if test="criteria.valid">
          <trim prefix="(" prefixOverrides="and" suffix=")">
            <foreach collection="criteria.criteria" item="criterion">
              <choose>
                <when test="criterion.noValue">
                  and ${criterion.condition}
                </when>
                <when test="criterion.singleValue">
                  and ${criterion.condition} #{criterion.value}
                </when>
                <when test="criterion.betweenValue">
                  and ${criterion.condition} #{criterion.value} and #{criterion.secondValue}
                </when>
                <when test="criterion.listValue">
                  and ${criterion.condition}
                  <foreach close=")" collection="criterion.value" item="listItem" open="(" separator=",">
                    #{listItem}
                  </foreach>
                </when>
              </choose>
            </foreach>
          </trim>
        </if>
      </foreach>
    </where>
  </sql>
  <sql id="Base_Column_List">
    <!--
      WARNING - @mbggenerated
      This element is automatically generated by MyBatis Generator, do not modify.
      This element was generated on Sun Nov 21 21:36:06 CST 2010.
    -->
    PRDCDE, EVTCDE, CTPCDE, CATCDE, ERYSEQ, ORGIDT, CUSIDT, APCODE, CURCDE, ERYAMT, CDRFLG, 
    VCHPAR, TOTNUM, CORCUR, CORAPC, ERYREM, AMDTLR, UPDDAT, RECSTS
  </sql>
  <select id="selectByExample" parameterType="cbs.repository.code.model.ActeryExample" resultMap="BaseResultMap">
    <!--
      WARNING - @mbggenerated
      This element is automatically generated by MyBatis Generator, do not modify.
      This element was generated on Sun Nov 21 21:36:06 CST 2010.
    -->
    select
    <if test="distinct">
      distinct
    </if>
    <include refid="Base_Column_List" />
    from ACTERY
    <if test="_parameter != null">
      <include refid="Example_Where_Clause" />
    </if>
    <if test="orderByClause != null">
      order by ${orderByClause}
    </if>
  </select>
  <delete id="deleteByExample" parameterType="cbs.repository.code.model.ActeryExample">
    <!--
      WARNING - @mbggenerated
      This element is automatically generated by MyBatis Generator, do not modify.
      This element was generated on Sun Nov 21 21:36:06 CST 2010.
    -->
    delete from ACTERY
    <if test="_parameter != null">
      <include refid="Example_Where_Clause" />
    </if>
  </delete>
  <insert id="insert" parameterType="cbs.repository.code.model.Actery">
    <!--
      WARNING - @mbggenerated
      This element is automatically generated by MyBatis Generator, do not modify.
      This element was generated on Sun Nov 21 21:36:06 CST 2010.
    -->
    insert into ACTERY (PRDCDE, EVTCDE, CTPCDE, 
      CATCDE, ERYSEQ, ORGIDT, 
      CUSIDT, APCODE, CURCDE, 
      ERYAMT, CDRFLG, VCHPAR, 
      TOTNUM, CORCUR, CORAPC, 
      ERYREM, AMDTLR, UPDDAT, 
      RECSTS)
    values (#{prdcde,jdbcType=VARCHAR}, #{evtcde,jdbcType=VARCHAR}, #{ctpcde,jdbcType=VARCHAR}, 
      #{catcde,jdbcType=VARCHAR}, #{eryseq,jdbcType=DECIMAL}, #{orgidt,jdbcType=VARCHAR}, 
      #{cusidt,jdbcType=VARCHAR}, #{apcode,jdbcType=VARCHAR}, #{curcde,jdbcType=VARCHAR}, 
      #{eryamt,jdbcType=VARCHAR}, #{cdrflg,jdbcType=DECIMAL}, #{vchpar,jdbcType=VARCHAR}, 
      #{totnum,jdbcType=DECIMAL}, #{corcur,jdbcType=VARCHAR}, #{corapc,jdbcType=VARCHAR}, 
      #{eryrem,jdbcType=VARCHAR}, #{amdtlr,jdbcType=VARCHAR}, #{upddat,jdbcType=TIMESTAMP}, 
      #{recsts,jdbcType=VARCHAR})
  </insert>
  <insert id="insertSelective" parameterType="cbs.repository.code.model.Actery">
    <!--
      WARNING - @mbggenerated
      This element is automatically generated by MyBatis Generator, do not modify.
      This element was generated on Sun Nov 21 21:36:06 CST 2010.
    -->
    insert into ACTERY
    <trim prefix="(" suffix=")" suffixOverrides=",">
      <if test="prdcde != null">
        PRDCDE,
      </if>
      <if test="evtcde != null">
        EVTCDE,
      </if>
      <if test="ctpcde != null">
        CTPCDE,
      </if>
      <if test="catcde != null">
        CATCDE,
      </if>
      <if test="eryseq != null">
        ERYSEQ,
      </if>
      <if test="orgidt != null">
        ORGIDT,
      </if>
      <if test="cusidt != null">
        CUSIDT,
      </if>
      <if test="apcode != null">
        APCODE,
      </if>
      <if test="curcde != null">
        CURCDE,
      </if>
      <if test="eryamt != null">
        ERYAMT,
      </if>
      <if test="cdrflg != null">
        CDRFLG,
      </if>
      <if test="vchpar != null">
        VCHPAR,
      </if>
      <if test="totnum != null">
        TOTNUM,
      </if>
      <if test="corcur != null">
        CORCUR,
      </if>
      <if test="corapc != null">
        CORAPC,
      </if>
      <if test="eryrem != null">
        ERYREM,
      </if>
      <if test="amdtlr != null">
        AMDTLR,
      </if>
      <if test="upddat != null">
        UPDDAT,
      </if>
      <if test="recsts != null">
        RECSTS,
      </if>
    </trim>
    <trim prefix="values (" suffix=")" suffixOverrides=",">
      <if test="prdcde != null">
        #{prdcde,jdbcType=VARCHAR},
      </if>
      <if test="evtcde != null">
        #{evtcde,jdbcType=VARCHAR},
      </if>
      <if test="ctpcde != null">
        #{ctpcde,jdbcType=VARCHAR},
      </if>
      <if test="catcde != null">
        #{catcde,jdbcType=VARCHAR},
      </if>
      <if test="eryseq != null">
        #{eryseq,jdbcType=DECIMAL},
      </if>
      <if test="orgidt != null">
        #{orgidt,jdbcType=VARCHAR},
      </if>
      <if test="cusidt != null">
        #{cusidt,jdbcType=VARCHAR},
      </if>
      <if test="apcode != null">
        #{apcode,jdbcType=VARCHAR},
      </if>
      <if test="curcde != null">
        #{curcde,jdbcType=VARCHAR},
      </if>
      <if test="eryamt != null">
        #{eryamt,jdbcType=VARCHAR},
      </if>
      <if test="cdrflg != null">
        #{cdrflg,jdbcType=DECIMAL},
      </if>
      <if test="vchpar != null">
        #{vchpar,jdbcType=VARCHAR},
      </if>
      <if test="totnum != null">
        #{totnum,jdbcType=DECIMAL},
      </if>
      <if test="corcur != null">
        #{corcur,jdbcType=VARCHAR},
      </if>
      <if test="corapc != null">
        #{corapc,jdbcType=VARCHAR},
      </if>
      <if test="eryrem != null">
        #{eryrem,jdbcType=VARCHAR},
      </if>
      <if test="amdtlr != null">
        #{amdtlr,jdbcType=VARCHAR},
      </if>
      <if test="upddat != null">
        #{upddat,jdbcType=TIMESTAMP},
      </if>
      <if test="recsts != null">
        #{recsts,jdbcType=VARCHAR},
      </if>
    </trim>
  </insert>
  <select id="countByExample" parameterType="cbs.repository.code.model.ActeryExample" resultType="java.lang.Integer">
    <!--
      WARNING - @mbggenerated
      This element is automatically generated by MyBatis Generator, do not modify.
      This element was generated on Sun Nov 21 21:36:06 CST 2010.
    -->
    select count(*) from ACTERY
    <if test="_parameter != null">
      <include refid="Example_Where_Clause" />
    </if>
  </select>
  <update id="updateByExampleSelective" parameterType="map">
    <!--
      WARNING - @mbggenerated
      This element is automatically generated by MyBatis Generator, do not modify.
      This element was generated on Sun Nov 21 21:36:06 CST 2010.
    -->
    update ACTERY
    <set>
      <if test="record.prdcde != null">
        PRDCDE = #{record.prdcde,jdbcType=VARCHAR},
      </if>
      <if test="record.evtcde != null">
        EVTCDE = #{record.evtcde,jdbcType=VARCHAR},
      </if>
      <if test="record.ctpcde != null">
        CTPCDE = #{record.ctpcde,jdbcType=VARCHAR},
      </if>
      <if test="record.catcde != null">
        CATCDE = #{record.catcde,jdbcType=VARCHAR},
      </if>
      <if test="record.eryseq != null">
        ERYSEQ = #{record.eryseq,jdbcType=DECIMAL},
      </if>
      <if test="record.orgidt != null">
        ORGIDT = #{record.orgidt,jdbcType=VARCHAR},
      </if>
      <if test="record.cusidt != null">
        CUSIDT = #{record.cusidt,jdbcType=VARCHAR},
      </if>
      <if test="record.apcode != null">
        APCODE = #{record.apcode,jdbcType=VARCHAR},
      </if>
      <if test="record.curcde != null">
        CURCDE = #{record.curcde,jdbcType=VARCHAR},
      </if>
      <if test="record.eryamt != null">
        ERYAMT = #{record.eryamt,jdbcType=VARCHAR},
      </if>
      <if test="record.cdrflg != null">
        CDRFLG = #{record.cdrflg,jdbcType=DECIMAL},
      </if>
      <if test="record.vchpar != null">
        VCHPAR = #{record.vchpar,jdbcType=VARCHAR},
      </if>
      <if test="record.totnum != null">
        TOTNUM = #{record.totnum,jdbcType=DECIMAL},
      </if>
      <if test="record.corcur != null">
        CORCUR = #{record.corcur,jdbcType=VARCHAR},
      </if>
      <if test="record.corapc != null">
        CORAPC = #{record.corapc,jdbcType=VARCHAR},
      </if>
      <if test="record.eryrem != null">
        ERYREM = #{record.eryrem,jdbcType=VARCHAR},
      </if>
      <if test="record.amdtlr != null">
        AMDTLR = #{record.amdtlr,jdbcType=VARCHAR},
      </if>
      <if test="record.upddat != null">
        UPDDAT = #{record.upddat,jdbcType=TIMESTAMP},
      </if>
      <if test="record.recsts != null">
        RECSTS = #{record.recsts,jdbcType=VARCHAR},
      </if>
    </set>
    <if test="_parameter != null">
      <include refid="Update_By_Example_Where_Clause" />
    </if>
  </update>
  <update id="updateByExample" parameterType="map">
    <!--
      WARNING - @mbggenerated
      This element is automatically generated by MyBatis Generator, do not modify.
      This element was generated on Sun Nov 21 21:36:06 CST 2010.
    -->
    update ACTERY
    set PRDCDE = #{record.prdcde,jdbcType=VARCHAR},
      EVTCDE = #{record.evtcde,jdbcType=VARCHAR},
      CTPCDE = #{record.ctpcde,jdbcType=VARCHAR},
      CATCDE = #{record.catcde,jdbcType=VARCHAR},
      ERYSEQ = #{record.eryseq,jdbcType=DECIMAL},
      ORGIDT = #{record.orgidt,jdbcType=VARCHAR},
      CUSIDT = #{record.cusidt,jdbcType=VARCHAR},
      APCODE = #{record.apcode,jdbcType=VARCHAR},
      CURCDE = #{record.curcde,jdbcType=VARCHAR},
      ERYAMT = #{record.eryamt,jdbcType=VARCHAR},
      CDRFLG = #{record.cdrflg,jdbcType=DECIMAL},
      VCHPAR = #{record.vchpar,jdbcType=VARCHAR},
      TOTNUM = #{record.totnum,jdbcType=DECIMAL},
      CORCUR = #{record.corcur,jdbcType=VARCHAR},
      CORAPC = #{record.corapc,jdbcType=VARCHAR},
      ERYREM = #{record.eryrem,jdbcType=VARCHAR},
      AMDTLR = #{record.amdtlr,jdbcType=VARCHAR},
      UPDDAT = #{record.upddat,jdbcType=TIMESTAMP},
      RECSTS = #{record.recsts,jdbcType=VARCHAR}
    <if test="_parameter != null">
      <include refid="Update_By_Example_Where_Clause" />
    </if>
  </update>
</mapper>