<?xml version="1.0" encoding="UTF-8"?>
<!DOCTYPE mapper PUBLIC "-//mybatis.org//DTD Mapper 3.0//EN" "http://mybatis.org/dtd/mybatis-3-mapper.dtd">
<mapper namespace="cbs.repository.account.maininfo.dao.ActalbMapper">
  <resultMap id="BaseResultMap" type="cbs.repository.account.maininfo.model.Actalb">
    <!--
      WARNING - @mbggenerated
      This element is automatically generated by MyBatis Generator, do not modify.
      This element was generated on Sun Nov 21 21:36:05 CST 2010.
    -->
    <id column="ALCODE" jdbcType="CHAR" property="alcode" />
    <id column="CURCDE" jdbcType="CHAR" property="curcde" />
    <id column="ORGIDT" jdbcType="CHAR" property="orgidt" />
    <id column="RECTYP" jdbcType="CHAR" property="rectyp" />
    <result column="ALCNAM" jdbcType="CHAR" property="alcnam" />
    <result column="ALCTYP" jdbcType="CHAR" property="alctyp" />
    <result column="COLNUM" jdbcType="CHAR" property="colnum" />
    <result column="LINFLG" jdbcType="CHAR" property="linflg" />
    <result column="CREDAT" jdbcType="TIMESTAMP" property="credat" />
    <result column="ALBBAL" jdbcType="DECIMAL" property="albbal" />
    <result column="ASTRBL" jdbcType="DECIMAL" property="astrbl" />
    <result column="RECSTS" jdbcType="CHAR" property="recsts" />
    <result column="SUMFLG" jdbcType="CHAR" property="sumflg" />
  </resultMap>
  <sql id="Example_Where_Clause">
    <!--
      WARNING - @mbggenerated
      This element is automatically generated by MyBatis Generator, do not modify.
      This element was generated on Sun Nov 21 21:36:05 CST 2010.
    -->
    <where>
      <foreach collection="oredCriteria" item="criteria" separator="or">
        <if test="criteria.valid">
          <trim prefix="(" prefixOverrides="and" suffix=")">
            <foreach collection="criteria.criteria" item="criterion">
              <choose>
                <when test="criterion.noValue">
                  and ${criterion.condition}
                </when>
                <when test="criterion.singleValue">
                  and ${criterion.condition} #{criterion.value}
                </when>
                <when test="criterion.betweenValue">
                  and ${criterion.condition} #{criterion.value} and #{criterion.secondValue}
                </when>
                <when test="criterion.listValue">
                  and ${criterion.condition}
                  <foreach close=")" collection="criterion.value" item="listItem" open="(" separator=",">
                    #{listItem}
                  </foreach>
                </when>
              </choose>
            </foreach>
          </trim>
        </if>
      </foreach>
    </where>
  </sql>
  <sql id="Update_By_Example_Where_Clause">
    <!--
      WARNING - @mbggenerated
      This element is automatically generated by MyBatis Generator, do not modify.
      This element was generated on Sun Nov 21 21:36:05 CST 2010.
    -->
    <where>
      <foreach collection="example.oredCriteria" item="criteria" separator="or">
        <if test="criteria.valid">
          <trim prefix="(" prefixOverrides="and" suffix=")">
            <foreach collection="criteria.criteria" item="criterion">
              <choose>
                <when test="criterion.noValue">
                  and ${criterion.condition}
                </when>
                <when test="criterion.singleValue">
                  and ${criterion.condition} #{criterion.value}
                </when>
                <when test="criterion.betweenValue">
                  and ${criterion.condition} #{criterion.value} and #{criterion.secondValue}
                </when>
                <when test="criterion.listValue">
                  and ${criterion.condition}
                  <foreach close=")" collection="criterion.value" item="listItem" open="(" separator=",">
                    #{listItem}
                  </foreach>
                </when>
              </choose>
            </foreach>
          </trim>
        </if>
      </foreach>
    </where>
  </sql>
  <sql id="Base_Column_List">
    <!--
      WARNING - @mbggenerated
      This element is automatically generated by MyBatis Generator, do not modify.
      This element was generated on Sun Nov 21 21:36:05 CST 2010.
    -->
    ALCODE, CURCDE, ORGIDT, RECTYP, ALCNAM, ALCTYP, COLNUM, LINFLG, CREDAT, ALBBAL, ASTRBL, 
    RECSTS, SUMFLG
  </sql>
  <select id="selectByExample" parameterType="cbs.repository.account.maininfo.model.ActalbExample" resultMap="BaseResultMap">
    <!--
      WARNING - @mbggenerated
      This element is automatically generated by MyBatis Generator, do not modify.
      This element was generated on Sun Nov 21 21:36:05 CST 2010.
    -->
    select
    <if test="distinct">
      distinct
    </if>
    <include refid="Base_Column_List" />
    from ACTALB
    <if test="_parameter != null">
      <include refid="Example_Where_Clause" />
    </if>
    <if test="orderByClause != null">
      order by ${orderByClause}
    </if>
  </select>
  <select id="selectByPrimaryKey" parameterType="cbs.repository.account.maininfo.model.ActalbKey" resultMap="BaseResultMap">
    <!--
      WARNING - @mbggenerated
      This element is automatically generated by MyBatis Generator, do not modify.
      This element was generated on Sun Nov 21 21:36:05 CST 2010.
    -->
    select 
    <include refid="Base_Column_List" />
    from ACTALB
    where ALCODE = #{alcode,jdbcType=CHAR}
      and CURCDE = #{curcde,jdbcType=CHAR}
      and ORGIDT = #{orgidt,jdbcType=CHAR}
      and RECTYP = #{rectyp,jdbcType=CHAR}
  </select>
  <delete id="deleteByPrimaryKey" parameterType="cbs.repository.account.maininfo.model.ActalbKey">
    <!--
      WARNING - @mbggenerated
      This element is automatically generated by MyBatis Generator, do not modify.
      This element was generated on Sun Nov 21 21:36:05 CST 2010.
    -->
    delete from ACTALB
    where ALCODE = #{alcode,jdbcType=CHAR}
      and CURCDE = #{curcde,jdbcType=CHAR}
      and ORGIDT = #{orgidt,jdbcType=CHAR}
      and RECTYP = #{rectyp,jdbcType=CHAR}
  </delete>
  <delete id="deleteByExample" parameterType="cbs.repository.account.maininfo.model.ActalbExample">
    <!--
      WARNING - @mbggenerated
      This element is automatically generated by MyBatis Generator, do not modify.
      This element was generated on Sun Nov 21 21:36:05 CST 2010.
    -->
    delete from ACTALB
    <if test="_parameter != null">
      <include refid="Example_Where_Clause" />
    </if>
  </delete>
  <insert id="insert" parameterType="cbs.repository.account.maininfo.model.Actalb">
    <!--
      WARNING - @mbggenerated
      This element is automatically generated by MyBatis Generator, do not modify.
      This element was generated on Sun Nov 21 21:36:05 CST 2010.
    -->
    insert into ACTALB (ALCODE, CURCDE, ORGIDT, 
      RECTYP, ALCNAM, ALCTYP, COLNUM, 
      LINFLG, CREDAT, ALBBAL, 
      ASTRBL, RECSTS, SUMFLG)
    values (#{alcode,jdbcType=CHAR}, #{curcde,jdbcType=CHAR}, #{orgidt,jdbcType=CHAR}, 
      #{rectyp,jdbcType=CHAR}, #{alcnam,jdbcType=CHAR}, #{alctyp,jdbcType=CHAR}, #{colnum,jdbcType=CHAR}, 
      #{linflg,jdbcType=CHAR}, #{credat,jdbcType=TIMESTAMP}, #{albbal,jdbcType=DECIMAL}, 
      #{astrbl,jdbcType=DECIMAL}, #{recsts,jdbcType=CHAR}, #{sumflg,jdbcType=CHAR})
  </insert>
  <insert id="insertSelective" parameterType="cbs.repository.account.maininfo.model.Actalb">
    <!--
      WARNING - @mbggenerated
      This element is automatically generated by MyBatis Generator, do not modify.
      This element was generated on Sun Nov 21 21:36:05 CST 2010.
    -->
    insert into ACTALB
    <trim prefix="(" suffix=")" suffixOverrides=",">
      <if test="alcode != null">
        ALCODE,
      </if>
      <if test="curcde != null">
        CURCDE,
      </if>
      <if test="orgidt != null">
        ORGIDT,
      </if>
      <if test="rectyp != null">
        RECTYP,
      </if>
      <if test="alcnam != null">
        ALCNAM,
      </if>
      <if test="alctyp != null">
        ALCTYP,
      </if>
      <if test="colnum != null">
        COLNUM,
      </if>
      <if test="linflg != null">
        LINFLG,
      </if>
      <if test="credat != null">
        CREDAT,
      </if>
      <if test="albbal != null">
        ALBBAL,
      </if>
      <if test="astrbl != null">
        ASTRBL,
      </if>
      <if test="recsts != null">
        RECSTS,
      </if>
      <if test="sumflg != null">
        SUMFLG,
      </if>
    </trim>
    <trim prefix="values (" suffix=")" suffixOverrides=",">
      <if test="alcode != null">
        #{alcode,jdbcType=CHAR},
      </if>
      <if test="curcde != null">
        #{curcde,jdbcType=CHAR},
      </if>
      <if test="orgidt != null">
        #{orgidt,jdbcType=CHAR},
      </if>
      <if test="rectyp != null">
        #{rectyp,jdbcType=CHAR},
      </if>
      <if test="alcnam != null">
        #{alcnam,jdbcType=CHAR},
      </if>
      <if test="alctyp != null">
        #{alctyp,jdbcType=CHAR},
      </if>
      <if test="colnum != null">
        #{colnum,jdbcType=CHAR},
      </if>
      <if test="linflg != null">
        #{linflg,jdbcType=CHAR},
      </if>
      <if test="credat != null">
        #{credat,jdbcType=TIMESTAMP},
      </if>
      <if test="albbal != null">
        #{albbal,jdbcType=DECIMAL},
      </if>
      <if test="astrbl != null">
        #{astrbl,jdbcType=DECIMAL},
      </if>
      <if test="recsts != null">
        #{recsts,jdbcType=CHAR},
      </if>
      <if test="sumflg != null">
        #{sumflg,jdbcType=CHAR},
      </if>
    </trim>
  </insert>
  <select id="countByExample" parameterType="cbs.repository.account.maininfo.model.ActalbExample" resultType="java.lang.Integer">
    <!--
      WARNING - @mbggenerated
      This element is automatically generated by MyBatis Generator, do not modify.
      This element was generated on Sun Nov 21 21:36:05 CST 2010.
    -->
    select count(*) from ACTALB
    <if test="_parameter != null">
      <include refid="Example_Where_Clause" />
    </if>
  </select>
  <update id="updateByExampleSelective" parameterType="map">
    <!--
      WARNING - @mbggenerated
      This element is automatically generated by MyBatis Generator, do not modify.
      This element was generated on Sun Nov 21 21:36:05 CST 2010.
    -->
    update ACTALB
    <set>
      <if test="record.alcode != null">
        ALCODE = #{record.alcode,jdbcType=CHAR},
      </if>
      <if test="record.curcde != null">
        CURCDE = #{record.curcde,jdbcType=CHAR},
      </if>
      <if test="record.orgidt != null">
        ORGIDT = #{record.orgidt,jdbcType=CHAR},
      </if>
      <if test="record.rectyp != null">
        RECTYP = #{record.rectyp,jdbcType=CHAR},
      </if>
      <if test="record.alcnam != null">
        ALCNAM = #{record.alcnam,jdbcType=CHAR},
      </if>
      <if test="record.alctyp != null">
        ALCTYP = #{record.alctyp,jdbcType=CHAR},
      </if>
      <if test="record.colnum != null">
        COLNUM = #{record.colnum,jdbcType=CHAR},
      </if>
      <if test="record.linflg != null">
        LINFLG = #{record.linflg,jdbcType=CHAR},
      </if>
      <if test="record.credat != null">
        CREDAT = #{record.credat,jdbcType=TIMESTAMP},
      </if>
      <if test="record.albbal != null">
        ALBBAL = #{record.albbal,jdbcType=DECIMAL},
      </if>
      <if test="record.astrbl != null">
        ASTRBL = #{record.astrbl,jdbcType=DECIMAL},
      </if>
      <if test="record.recsts != null">
        RECSTS = #{record.recsts,jdbcType=CHAR},
      </if>
      <if test="record.sumflg != null">
        SUMFLG = #{record.sumflg,jdbcType=CHAR},
      </if>
    </set>
    <if test="_parameter != null">
      <include refid="Update_By_Example_Where_Clause" />
    </if>
  </update>
  <update id="updateByExample" parameterType="map">
    <!--
      WARNING - @mbggenerated
      This element is automatically generated by MyBatis Generator, do not modify.
      This element was generated on Sun Nov 21 21:36:05 CST 2010.
    -->
    update ACTALB
    set ALCODE = #{record.alcode,jdbcType=CHAR},
      CURCDE = #{record.curcde,jdbcType=CHAR},
      ORGIDT = #{record.orgidt,jdbcType=CHAR},
      RECTYP = #{record.rectyp,jdbcType=CHAR},
      ALCNAM = #{record.alcnam,jdbcType=CHAR},
      ALCTYP = #{record.alctyp,jdbcType=CHAR},
      COLNUM = #{record.colnum,jdbcType=CHAR},
      LINFLG = #{record.linflg,jdbcType=CHAR},
      CREDAT = #{record.credat,jdbcType=TIMESTAMP},
      ALBBAL = #{record.albbal,jdbcType=DECIMAL},
      ASTRBL = #{record.astrbl,jdbcType=DECIMAL},
      RECSTS = #{record.recsts,jdbcType=CHAR},
      SUMFLG = #{record.sumflg,jdbcType=CHAR}
    <if test="_parameter != null">
      <include refid="Update_By_Example_Where_Clause" />
    </if>
  </update>
  <update id="updateByPrimaryKeySelective" parameterType="cbs.repository.account.maininfo.model.Actalb">
    <!--
      WARNING - @mbggenerated
      This element is automatically generated by MyBatis Generator, do not modify.
      This element was generated on Sun Nov 21 21:36:05 CST 2010.
    -->
    update ACTALB
    <set>
      <if test="alcnam != null">
        ALCNAM = #{alcnam,jdbcType=CHAR},
      </if>
      <if test="alctyp != null">
        ALCTYP = #{alctyp,jdbcType=CHAR},
      </if>
      <if test="colnum != null">
        COLNUM = #{colnum,jdbcType=CHAR},
      </if>
      <if test="linflg != null">
        LINFLG = #{linflg,jdbcType=CHAR},
      </if>
      <if test="credat != null">
        CREDAT = #{credat,jdbcType=TIMESTAMP},
      </if>
      <if test="albbal != null">
        ALBBAL = #{albbal,jdbcType=DECIMAL},
      </if>
      <if test="astrbl != null">
        ASTRBL = #{astrbl,jdbcType=DECIMAL},
      </if>
      <if test="recsts != null">
        RECSTS = #{recsts,jdbcType=CHAR},
      </if>
      <if test="sumflg != null">
        SUMFLG = #{sumflg,jdbcType=CHAR},
      </if>
    </set>
    where ALCODE = #{alcode,jdbcType=CHAR}
      and CURCDE = #{curcde,jdbcType=CHAR}
      and ORGIDT = #{orgidt,jdbcType=CHAR}
      and RECTYP = #{rectyp,jdbcType=CHAR}
  </update>
  <update id="updateByPrimaryKey" parameterType="cbs.repository.account.maininfo.model.Actalb">
    <!--
      WARNING - @mbggenerated
      This element is automatically generated by MyBatis Generator, do not modify.
      This element was generated on Sun Nov 21 21:36:05 CST 2010.
    -->
    update ACTALB
    set ALCNAM = #{alcnam,jdbcType=CHAR},
      ALCTYP = #{alctyp,jdbcType=CHAR},
      COLNUM = #{colnum,jdbcType=CHAR},
      LINFLG = #{linflg,jdbcType=CHAR},
      CREDAT = #{credat,jdbcType=TIMESTAMP},
      ALBBAL = #{albbal,jdbcType=DECIMAL},
      ASTRBL = #{astrbl,jdbcType=DECIMAL},
      RECSTS = #{recsts,jdbcType=CHAR},
      SUMFLG = #{sumflg,jdbcType=CHAR}
    where ALCODE = #{alcode,jdbcType=CHAR}
      and CURCDE = #{curcde,jdbcType=CHAR}
      and ORGIDT = #{orgidt,jdbcType=CHAR}
      and RECTYP = #{rectyp,jdbcType=CHAR}
  </update>
</mapper>